poetry_demo_20230621/__init__.py
poetry_demo_20230621-0.1.1.dist-info/METADATA
poetry_demo_20230621-0.1.1.dist-info/WHEEL
poetry_demo_20230621-0.1.1.dist-info/RECORD
