Metadata-Version: 2.1
Name: poetry-demo-20230621
Version: 0.1.1
Summary: 
Author: Fateme Tardasti
Author-email: fateme.tardasti@alexanderthamm.com
Requires-Python: >=3.11,<4.0
Classifier: Programming Language :: Python :: 3
Classifier: Programming Language :: Python :: 3.11
Requires-Dist: numpy (>=1.25.0,<2.0.0)
